<?xml version="1.0" encoding="utf-8" ?>
<dwsync>
<file name="wp-config.php" server="ftp.rockn-w-ranch.com//adamgilson/" local="129246840000000000" remote="129246840000000000" />
<file name="wp-atom.php" server="ftp.rockn-w-ranch.com//adamgilson/" local="129635620200000000" remote="129635620200000000" />
<file name="wp-commentsrss2.php" server="ftp.rockn-w-ranch.com//adamgilson/" local="129635620200000000" remote="129635620200000000" />
<file name="wp-feed.php" server="ftp.rockn-w-ranch.com//adamgilson/" local="129635620200000000" remote="129635620200000000" />
<file name="wp-rdf.php" server="ftp.rockn-w-ranch.com//adamgilson/" local="129635620200000000" remote="129635620200000000" />
<file name="wp-rss.php" server="ftp.rockn-w-ranch.com//adamgilson/" local="129635620200000000" remote="129635620200000000" />
<file name="wp-rss2.php" server="ftp.rockn-w-ranch.com//adamgilson/" local="129635620200000000" remote="129635620200000000" />
<file name="index.php" server="ftp.rockn-w-ranch.com//adamgilson/" local="129734964000000000" remote="129734964000000000" />
<file name="license.txt" server="ftp.rockn-w-ranch.com//adamgilson/" local="129734964000000000" remote="129734964000000000" />
<file name="readme.html" server="ftp.rockn-w-ranch.com//adamgilson/" local="129734964000000000" remote="129734964000000000" />
<file name="wp-activate.php" server="ftp.rockn-w-ranch.com//adamgilson/" local="129734964000000000" remote="129734964000000000" />
<file name="wp-app.php" server="ftp.rockn-w-ranch.com//adamgilson/" local="129734964000000000" remote="129734964000000000" />
<file name="wp-blog-header.php" server="ftp.rockn-w-ranch.com//adamgilson/" local="129734964000000000" remote="129734964000000000" />
<file name="wp-comments-post.php" server="ftp.rockn-w-ranch.com//adamgilson/" local="129734964000000000" remote="129734964000000000" />
<file name="wp-config-sample.php" server="ftp.rockn-w-ranch.com//adamgilson/" local="129734964000000000" remote="129734964000000000" />
<file name="wp-cron.php" server="ftp.rockn-w-ranch.com//adamgilson/" local="129734964000000000" remote="129734964000000000" />
<file name="wp-links-opml.php" server="ftp.rockn-w-ranch.com//adamgilson/" local="129734964000000000" remote="129734964000000000" />
<file name="wp-load.php" server="ftp.rockn-w-ranch.com//adamgilson/" local="129734964000000000" remote="129734964000000000" />
<file name="wp-login.php" server="ftp.rockn-w-ranch.com//adamgilson/" local="129734964000000000" remote="129734964000000000" />
<file name="wp-mail.php" server="ftp.rockn-w-ranch.com//adamgilson/" local="129734964000000000" remote="129734964000000000" />
<file name="wp-pass.php" server="ftp.rockn-w-ranch.com//adamgilson/" local="129734964000000000" remote="129734964000000000" />
<file name="wp-register.php" server="ftp.rockn-w-ranch.com//adamgilson/" local="129734964000000000" remote="129734964000000000" />
<file name="wp-settings.php" server="ftp.rockn-w-ranch.com//adamgilson/" local="129734964000000000" remote="129734964000000000" />
<file name="wp-signup.php" server="ftp.rockn-w-ranch.com//adamgilson/" local="129734964000000000" remote="129734964000000000" />
<file name="wp-trackback.php" server="ftp.rockn-w-ranch.com//adamgilson/" local="129734964000000000" remote="129734964000000000" />
<file name="xmlrpc.php" server="ftp.rockn-w-ranch.com//adamgilson/" local="129734964000000000" remote="129734964000000000" />
</dwsync>